y2mate_api/__init__.py
y2mate_api/__main__.py
y2mate_api/console.py
y2mate_api/downloader.py
y2mate_api/main.py
y2mate_api-1.2.2.dist-info/LICENSE
y2mate_api-1.2.2.dist-info/METADATA
y2mate_api-1.2.2.dist-info/WHEEL
y2mate_api-1.2.2.dist-info/entry_points.txt
y2mate_api-1.2.2.dist-info/top_level.txt
y2mate_api-1.2.2.dist-info/RECORD
