Metadata-Version: 2.1
Name: y2mate-api
Version: 1.2.2
Summary: Download youtube videos and audios by title or link
Home-page: https://github.com/Simatwa/y2mate-api
Author: Smartwa
Author-email: smartwacaleb@gmail.com
Maintainer: Smartwa
License: MIT
Project-URL: Bug Report, https://github.com/Simatwa/y2mate-api/issues/new
Keywords: y2mate,videos,video-api,youtube,youtube-api,youtube-dl,y2mate-api
Classifier: License :: OSI Approved :: MIT License
Classifier: Development Status :: 4 - Beta
Classifier: Intended Audience :: Developers
Classifier: Natural Language :: English
Classifier: License :: Free For Home Use
Classifier: Intended Audience :: Customer Service
Classifier: Programming Language :: Python
Classifier: Topic :: Software Development :: Libraries :: Python Modules
Classifier: Programming Language :: Python :: 3 :: Only
Classifier: Programming Language :: Python :: 3.9
Classifier: Programming Language :: Python :: 3.10
Classifier: Programming Language :: Python :: 3.11
Classifier: Programming Language :: Python :: 3.12
Requires-Python: >=3.9
License-File: LICENSE
Requires-Dist: argparse >=1.1
Requires-Dist: tqdm ==4.65.0
Requires-Dist: requests ==2.31.0
Requires-Dist: colorama ==0.4.6
Requires-Dist: appdirs ==1.4.4
Requires-Dist: click ==8.1.3
Requires-Dist: curl-cffi ==0.7.2
